langchain_to_mcp_tool_adapter/__init__.py
langchain_to_mcp_tool_adapter/adapter.py
langchain_to_mcp_tool_adapter-0.1.3.dist-info/licenses/LICENSE
tests/__init__.py
tests/conftest.py
tests/test_adapters.py
tests/test_convert.py
tests/test_tools.py
langchain_to_mcp_tool_adapter-0.1.3.dist-info/METADATA
langchain_to_mcp_tool_adapter-0.1.3.dist-info/WHEEL
langchain_to_mcp_tool_adapter-0.1.3.dist-info/top_level.txt
langchain_to_mcp_tool_adapter-0.1.3.dist-info/RECORD
