Metadata-Version: 2.4
Name: langchain-to-mcp-tool-adapter
Version: 0.1.3
Summary: Adapter for converting LangChain tools to FastMCP tools
Home-page: https://github.com/dovstern/langchain-to-mcp-tool-adapter
Author: LangChain to MCP Tool Adapter Contributors
Author-email: maintainers@example.com
Classifier: Programming Language :: Python :: 3
Classifier: Programming Language :: Python :: 3.10
Classifier: Programming Language :: Python :: 3.11
Classifier: License :: OSI Approved :: MIT License
Classifier: Operating System :: OS Independent
Classifier: Development Status :: 4 - Beta
Classifier: Intended Audience :: Developers
Classifier: Topic :: Software Development :: Libraries :: Python Modules
Requires-Python: >=3.10
License-File: LICENSE
Requires-Dist: langchain<0.4.0,>=0.1.0
Requires-Dist: fastmcp>=2.2.0
Requires-Dist: pydantic<3.0.0,>=2.0.0
Provides-Extra: dev
Requires-Dist: pytest>=7.0.0; extra == "dev"
Requires-Dist: black>=23.0.0; extra == "dev"
Requires-Dist: isort>=5.0.0; extra == "dev"
Requires-Dist: flake8>=5.0.0; extra == "dev"
Requires-Dist: langchain-mcp-adapters; extra == "dev"
Requires-Dist: langgraph; extra == "dev"
Requires-Dist: langchain-openai; extra == "dev"
Requires-Dist: twine>=4.0.0; extra == "dev"
Requires-Dist: build>=0.10.0; extra == "dev"
Dynamic: author
Dynamic: author-email
Dynamic: classifier
Dynamic: description
Dynamic: description-content-type
Dynamic: home-page
Dynamic: license-file
Dynamic: provides-extra
Dynamic: requires-dist
Dynamic: requires-python
Dynamic: summary
